{
  "json_class": "RPG::Map",
  "bgm": {
    "json_class": "RPG::AudioFile",
    "volume": 80,
    "name": "Battle Frontier",
    "pitch": 100
  },
  "events": {
    "1": {
      "json_class": "RPG::Event",
      "pages": [
        {
          "json_class": "RPG::Event::Page",
          "list": [
            {
              "json_class": "RPG::EventCommand",
              "parameters": [
                0,
                {
                  "json_class": "RPG::MoveRoute",
                  "list": [
                    {
                      "json_class": "RPG::MoveCommand",
                      "parameters": [],
                      "code": 4
                    },
                    {
                      "json_class": "RPG::MoveCommand",
                      "parameters": [],
                      "code": 4
                    },
                    {
                      "json_class": "RPG::MoveCommand",
                      "parameters": [],
                      "code": 4
                    },
                    {
                      "json_class": "RPG::MoveCommand",
                      "parameters": [],
                      "code": 18
                    },
                    {
                      "json_class": "RPG::MoveCommand",
                      "parameters": [],
                      "code": 38
                    },
                    {
                      "json_class": "RPG::MoveCommand",
                      "parameters": [],
                      "code": 0
                    }
                  ],
                  "skippable": false,
                  "repeat": false
                }
              ],
              "indent": 0,
              "code": 209
            },
            {
              "json_class": "RPG::EventCommand",
              "parameters": [
                {
                  "json_class": "RPG::MoveCommand",
                  "parameters": [],
                  "code": 4
                }
              ],
              "indent": 0,
              "code": 509
            },
            {
              "json_class": "RPG::EventCommand",
              "parameters": [
                {
                  "json_class": "RPG::MoveCommand",
                  "parameters": [],
                  "code": 4
                }
              ],
              "indent": 0,
              "code": 509
            },
            {
              "json_class": "RPG::EventCommand",
              "parameters": [
                {
                  "json_class": "RPG::MoveCommand",
                  "parameters": [],
                  "code": 4
                }
              ],
              "indent": 0,
              "code": 509
            },
            {
              "json_class": "RPG::EventCommand",
              "parameters": [
                {
                  "json_class": "RPG::MoveCommand",
                  "parameters": [],
                  "code": 18
                }
              ],
              "indent": 0,
              "code": 509
            },
            {
              "json_class": "RPG::EventCommand",
              "parameters": [
                {
                  "json_class": "RPG::MoveCommand",
                  "parameters": [],
                  "code": 38
                }
              ],
              "indent": 0,
              "code": 509
            },
            {
              "json_class": "RPG::EventCommand",
              "parameters": [
                -1,
                {
                  "json_class": "RPG::MoveRoute",
                  "list": [
                    {
                      "json_class": "RPG::MoveCommand",
                      "parameters": [
                        3
                      ],
                      "code": 29
                    },
                    {
                      "json_class": "RPG::MoveCommand",
                      "parameters": [
                        0
                      ],
                      "code": 42
                    },
                    {
                      "json_class": "RPG::MoveCommand",
                      "parameters": [],
                      "code": 37
                    },
                    {
                      "json_class": "RPG::MoveCommand",
                      "parameters": [],
                      "code": 4
                    },
                    {
                      "json_class": "RPG::MoveCommand",
                      "parameters": [
                        255
                      ],
                      "code": 42
                    },
                    {
                      "json_class": "RPG::MoveCommand",
                      "parameters": [],
                      "code": 4
                    },
                    {
                      "json_class": "RPG::MoveCommand",
                      "parameters": [],
                      "code": 4
                    },
                    {
                      "json_class": "RPG::MoveCommand",
                      "parameters": [],
                      "code": 3
                    },
                    {
                      "json_class": "RPG::MoveCommand",
                      "parameters": [],
                      "code": 4
                    },
                    {
                      "json_class": "RPG::MoveCommand",
                      "parameters": [],
                      "code": 3
                    },
                    {
                      "json_class": "RPG::MoveCommand",
                      "parameters": [],
                      "code": 3
                    },
                    {
                      "json_class": "RPG::MoveCommand",
                      "parameters": [],
                      "code": 38
                    },
                    {
                      "json_class": "RPG::MoveCommand",
                      "parameters": [],
                      "code": 0
                    }
                  ],
                  "skippable": false,
                  "repeat": false
                }
              ],
              "indent": 0,
              "code": 209
            },
            {
              "json_class": "RPG::EventCommand",
              "parameters": [
                {
                  "json_class": "RPG::MoveCommand",
                  "parameters": [
                    3
                  ],
                  "code": 29
                }
              ],
              "indent": 0,
              "code": 509
            },
            {
              "json_class": "RPG::EventCommand",
              "parameters": [
                {
                  "json_class": "RPG::MoveCommand",
                  "parameters": [
                    0
                  ],
                  "code": 42
                }
              ],
              "indent": 0,
              "code": 509
            },
            {
              "json_class": "RPG::EventCommand",
              "parameters": [
                {
                  "json_class": "RPG::MoveCommand",
                  "parameters": [],
                  "code": 37
                }
              ],
              "indent": 0,
              "code": 509
            },
            {
              "json_class": "RPG::EventCommand",
              "parameters": [
                {
                  "json_class": "RPG::MoveCommand",
                  "parameters": [],
                  "code": 4
                }
              ],
              "indent": 0,
              "code": 509
            },
            {
              "json_class": "RPG::EventCommand",
              "parameters": [
                {
                  "json_class": "RPG::MoveCommand",
                  "parameters": [
                    255
                  ],
                  "code": 42
                }
              ],
              "indent": 0,
              "code": 509
            },
            {
              "json_class": "RPG::EventCommand",
              "parameters": [
                {
                  "json_class": "RPG::MoveCommand",
                  "parameters": [],
                  "code": 4
                }
              ],
              "indent": 0,
              "code": 509
            },
            {
              "json_class": "RPG::EventCommand",
              "parameters": [
                {
                  "json_class": "RPG::MoveCommand",
                  "parameters": [],
                  "code": 4
                }
              ],
              "indent": 0,
              "code": 509
            },
            {
              "json_class": "RPG::EventCommand",
              "parameters": [
                {
                  "json_class": "RPG::MoveCommand",
                  "parameters": [],
                  "code": 3
                }
              ],
              "indent": 0,
              "code": 509
            },
            {
              "json_class": "RPG::EventCommand",
              "parameters": [
                {
                  "json_class": "RPG::MoveCommand",
                  "parameters": [],
                  "code": 4
                }
              ],
              "indent": 0,
              "code": 509
            },
            {
              "json_class": "RPG::EventCommand",
              "parameters": [
                {
                  "json_class": "RPG::MoveCommand",
                  "parameters": [],
                  "code": 3
                }
              ],
              "indent": 0,
              "code": 509
            },
            {
              "json_class": "RPG::EventCommand",
              "parameters": [
                {
                  "json_class": "RPG::MoveCommand",
                  "parameters": [],
                  "code": 3
                }
              ],
              "indent": 0,
              "code": 509
            },
            {
              "json_class": "RPG::EventCommand",
              "parameters": [
                {
                  "json_class": "RPG::MoveCommand",
                  "parameters": [],
                  "code": 38
                }
              ],
              "indent": 0,
              "code": 509
            },
            {
              "json_class": "RPG::EventCommand",
              "parameters": [],
              "indent": 0,
              "code": 210
            },
            {
              "json_class": "RPG::EventCommand",
              "parameters": [
                "pbSet(1,"
              ],
              "indent": 0,
              "code": 355
            },
            {
              "json_class": "RPG::EventCommand",
              "parameters": [
                "  pbBattleChallenge.battleNumber"
              ],
              "indent": 0,
              "code": 655
            },
            {
              "json_class": "RPG::EventCommand",
              "parameters": [
                ")"
              ],
              "indent": 0,
              "code": 655
            },
            {
              "json_class": "RPG::EventCommand",
              "parameters": [
                2,
                0,
                12,
                1,
                2
              ],
              "indent": 0,
              "code": 202
            },
            {
              "json_class": "RPG::EventCommand",
              "parameters": [
                "pbBattleChallengeGraphic(get_character(2))"
              ],
              "indent": 0,
              "code": 355
            },
            {
              "json_class": "RPG::EventCommand",
              "parameters": [
                2,
                {
                  "json_class": "RPG::MoveRoute",
                  "list": [
                    {
                      "json_class": "RPG::MoveCommand",
                      "parameters": [],
                      "code": 37
                    },
                    {
                      "json_class": "RPG::MoveCommand",
                      "parameters": [],
                      "code": 1
                    },
                    {
                      "json_class": "RPG::MoveCommand",
                      "parameters": [],
                      "code": 1
                    },
                    {
                      "json_class": "RPG::MoveCommand",
                      "parameters": [],
                      "code": 1
                    },
                    {
                      "json_class": "RPG::MoveCommand",
                      "parameters": [],
                      "code": 1
                    },
                    {
                      "json_class": "RPG::MoveCommand",
                      "parameters": [],
                      "code": 2
                    },
                    {
                      "json_class": "RPG::MoveCommand",
                      "parameters": [],
                      "code": 2
                    },
                    {
                      "json_class": "RPG::MoveCommand",
                      "parameters": [],
                      "code": 2
                    },
                    {
                      "json_class": "RPG::MoveCommand",
                      "parameters": [],
                      "code": 38
                    },
                    {
                      "json_class": "RPG::MoveCommand",
                      "parameters": [],
                      "code": 0
                    }
                  ],
                  "skippable": false,
                  "repeat": false
                }
              ],
              "indent": 0,
              "code": 209
            },
            {
              "json_class": "RPG::EventCommand",
              "parameters": [
                {
                  "json_class": "RPG::MoveCommand",
                  "parameters": [],
                  "code": 37
                }
              ],
              "indent": 0,
              "code": 509
            },
            {
              "json_class": "RPG::EventCommand",
              "parameters": [
                {
                  "json_class": "RPG::MoveCommand",
                  "parameters": [],
                  "code": 1
                }
              ],
              "indent": 0,
              "code": 509
            },
            {
              "json_class": "RPG::EventCommand",
              "parameters": [
                {
                  "json_class": "RPG::MoveCommand",
                  "parameters": [],
                  "code": 1
                }
              ],
              "indent": 0,
              "code": 509
            },
            {
              "json_class": "RPG::EventCommand",
              "parameters": [
                {
                  "json_class": "RPG::MoveCommand",
                  "parameters": [],
                  "code": 1
                }
              ],
              "indent": 0,
              "code": 509
            },
            {
              "json_class": "RPG::EventCommand",
              "parameters": [
                {
                  "json_class": "RPG::MoveCommand",
                  "parameters": [],
                  "code": 1
                }
              ],
              "indent": 0,
              "code": 509
            },
            {
              "json_class": "RPG::EventCommand",
              "parameters": [
                {
                  "json_class": "RPG::MoveCommand",
                  "parameters": [],
                  "code": 2
                }
              ],
              "indent": 0,
              "code": 509
            },
            {
              "json_class": "RPG::EventCommand",
              "parameters": [
                {
                  "json_class": "RPG::MoveCommand",
                  "parameters": [],
                  "code": 2
                }
              ],
              "indent": 0,
              "code": 509
            },
            {
              "json_class": "RPG::EventCommand",
              "parameters": [
                {
                  "json_class": "RPG::MoveCommand",
                  "parameters": [],
                  "code": 2
                }
              ],
              "indent": 0,
              "code": 509
            },
            {
              "json_class": "RPG::EventCommand",
              "parameters": [
                {
                  "json_class": "RPG::MoveCommand",
                  "parameters": [],
                  "code": 38
                }
              ],
              "indent": 0,
              "code": 509
            },
            {
              "json_class": "RPG::EventCommand",
              "parameters": [],
              "indent": 0,
              "code": 210
            },
            {
              "json_class": "RPG::EventCommand",
              "parameters": [
                "pbSet(1,"
              ],
              "indent": 0,
              "code": 355
            },
            {
              "json_class": "RPG::EventCommand",
              "parameters": [
                "  pbBattleChallengeBeginSpeech"
              ],
              "indent": 0,
              "code": 655
            },
            {
              "json_class": "RPG::EventCommand",
              "parameters": [
                ")"
              ],
              "indent": 0,
              "code": 655
            },
            {
              "json_class": "RPG::EventCommand",
              "parameters": [
                "\\v[1]"
              ],
              "indent": 0,
              "code": 101
            },
            {
              "json_class": "RPG::EventCommand",
              "parameters": [
                12,
                "pbBattleChallengeBattle"
              ],
              "indent": 0,
              "code": 111
            },
            {
              "json_class": "RPG::EventCommand",
              "parameters": [
                "pbBattleChallenge.pbAddWin"
              ],
              "indent": 1,
              "code": 355
            },
            {
              "json_class": "RPG::EventCommand",
              "parameters": [
                2,
                {
                  "json_class": "RPG::MoveRoute",
                  "list": [
                    {
                      "json_class": "RPG::MoveCommand",
                      "parameters": [],
                      "code": 37
                    },
                    {
                      "json_class": "RPG::MoveCommand",
                      "parameters": [],
                      "code": 3
                    },
                    {
                      "json_class": "RPG::MoveCommand",
                      "parameters": [],
                      "code": 3
                    },
                    {
                      "json_class": "RPG::MoveCommand",
                      "parameters": [],
                      "code": 3
                    },
                    {
                      "json_class": "RPG::MoveCommand",
                      "parameters": [],
                      "code": 4
                    },
                    {
                      "json_class": "RPG::MoveCommand",
                      "parameters": [],
                      "code": 4
                    },
                    {
                      "json_class": "RPG::MoveCommand",
                      "parameters": [],
                      "code": 4
                    },
                    {
                      "json_class": "RPG::MoveCommand",
                      "parameters": [],
                      "code": 4
                    },
                    {
                      "json_class": "RPG::MoveCommand",
                      "parameters": [
                        "",
                        0,
                        2,
                        0
                      ],
                      "code": 41
                    },
                    {
                      "json_class": "RPG::MoveCommand",
                      "parameters": [],
                      "code": 38
                    },
                    {
                      "json_class": "RPG::MoveCommand",
                      "parameters": [],
                      "code": 0
                    }
                  ],
                  "skippable": false,
                  "repeat": false
                }
              ],
              "indent": 1,
              "code": 209
            },
            {
              "json_class": "RPG::EventCommand",
              "parameters": [
                {
                  "json_class": "RPG::MoveCommand",
                  "parameters": [],
                  "code": 37
                }
              ],
              "indent": 1,
              "code": 509
            },
            {
              "json_class": "RPG::EventCommand",
              "parameters": [
                {
                  "json_class": "RPG::MoveCommand",
                  "parameters": [],
                  "code": 3
                }
              ],
              "indent": 1,
              "code": 509
            },
            {
              "json_class": "RPG::EventCommand",
              "parameters": [
                {
                  "json_class": "RPG::MoveCommand",
                  "parameters": [],
                  "code": 3
                }
              ],
              "indent": 1,
              "code": 509
            },
            {
              "json_class": "RPG::EventCommand",
              "parameters": [
                {
                  "json_class": "RPG::MoveCommand",
                  "parameters": [],
                  "code": 3
                }
              ],
              "indent": 1,
              "code": 509
            },
            {
              "json_class": "RPG::EventCommand",
              "parameters": [
                {
                  "json_class": "RPG::MoveCommand",
                  "parameters": [],
                  "code": 4
                }
              ],
              "indent": 1,
              "code": 509
            },
            {
              "json_class": "RPG::EventCommand",
              "parameters": [
                {
                  "json_class": "RPG::MoveCommand",
                  "parameters": [],
                  "code": 4
                }
              ],
              "indent": 1,
              "code": 509
            },
            {
              "json_class": "RPG::EventCommand",
              "parameters": [
                {
                  "json_class": "RPG::MoveCommand",
                  "parameters": [],
                  "code": 4
                }
              ],
              "indent": 1,
              "code": 509
            },
            {
              "json_class": "RPG::EventCommand",
              "parameters": [
                {
                  "json_class": "RPG::MoveCommand",
                  "parameters": [],
                  "code": 4
                }
              ],
              "indent": 1,
              "code": 509
            },
            {
              "json_class": "RPG::EventCommand",
              "parameters": [
                {
                  "json_class": "RPG::MoveCommand",
                  "parameters": [
                    "",
                    0,
                    2,
                    0
                  ],
                  "code": 41
                }
              ],
              "indent": 1,
              "code": 509
            },
            {
              "json_class": "RPG::EventCommand",
              "parameters": [
                {
                  "json_class": "RPG::MoveCommand",
                  "parameters": [],
                  "code": 38
                }
              ],
              "indent": 1,
              "code": 509
            },
            {
              "json_class": "RPG::EventCommand",
              "parameters": [],
              "indent": 1,
              "code": 210
            },
            {
              "json_class": "RPG::EventCommand",
              "parameters": [
                -1,
                {
                  "json_class": "RPG::MoveRoute",
                  "list": [
                    {
                      "json_class": "RPG::MoveCommand",
                      "parameters": [
                        3
                      ],
                      "code": 29
                    },
                    {
                      "json_class": "RPG::MoveCommand",
                      "parameters": [],
                      "code": 37
                    },
                    {
                      "json_class": "RPG::MoveCommand",
                      "parameters": [],
                      "code": 2
                    },
                    {
                      "json_class": "RPG::MoveCommand",
                      "parameters": [],
                      "code": 2
                    },
                    {
                      "json_class": "RPG::MoveCommand",
                      "parameters": [],
                      "code": 38
                    },
                    {
                      "json_class": "RPG::MoveCommand",
                      "parameters": [],
                      "code": 0
                    }
                  ],
                  "skippable": false,
                  "repeat": false
                }
              ],
              "indent": 1,
              "code": 209
            },
            {
              "json_class": "RPG::EventCommand",
              "parameters": [
                {
                  "json_class": "RPG::MoveCommand",
                  "parameters": [
                    3
                  ],
                  "code": 29
                }
              ],
              "indent": 1,
              "code": 509
            },
            {
              "json_class": "RPG::EventCommand",
              "parameters": [
                {
                  "json_class": "RPG::MoveCommand",
                  "parameters": [],
                  "code": 37
                }
              ],
              "indent": 1,
              "code": 509
            },
            {
              "json_class": "RPG::EventCommand",
              "parameters": [
                {
                  "json_class": "RPG::MoveCommand",
                  "parameters": [],
                  "code": 2
                }
              ],
              "indent": 1,
              "code": 509
            },
            {
              "json_class": "RPG::EventCommand",
              "parameters": [
                {
                  "json_class": "RPG::MoveCommand",
                  "parameters": [],
                  "code": 2
                }
              ],
              "indent": 1,
              "code": 509
            },
            {
              "json_class": "RPG::EventCommand",
              "parameters": [
                {
                  "json_class": "RPG::MoveCommand",
                  "parameters": [],
                  "code": 38
                }
              ],
              "indent": 1,
              "code": 509
            },
            {
              "json_class": "RPG::EventCommand",
              "parameters": [],
              "indent": 1,
              "code": 210
            },
            {
              "json_class": "RPG::EventCommand",
              "parameters": [
                12,
                "pbBattleChallenge.pbMatchOver?"
              ],
              "indent": 1,
              "code": 111
            },
            {
              "json_class": "RPG::EventCommand",
              "parameters": [
                "pbBattleChallenge.setDecision(1)"
              ],
              "indent": 2,
              "code": 355
            },
            {
              "json_class": "RPG::EventCommand",
              "parameters": [
                {
                  "json_class": "RPG::AudioFile",
                  "volume": 80,
                  "name": "Door exit",
                  "pitch": 100
                }
              ],
              "indent": 2,
              "code": 250
            },
            {
              "json_class": "RPG::EventCommand",
              "parameters": [
                {
                  "json_class": "Tone",
                  "red": -255.0,
                  "green": -255.0,
                  "blue": -255.0,
                  "gray": 0.0
                },
                6
              ],
              "indent": 2,
              "code": 223
            },
            {
              "json_class": "RPG::EventCommand",
              "parameters": [
                8
              ],
              "indent": 2,
              "code": 106
            },
            {
              "json_class": "RPG::EventCommand",
              "parameters": [
                "pbBattleChallenge.pbGoToStart"
              ],
              "indent": 2,
              "code": 355
            },
            {
              "json_class": "RPG::EventCommand",
              "parameters": [
                {
                  "json_class": "Tone",
                  "red": 0.0,
                  "green": 0.0,
                  "blue": 0.0,
                  "gray": 0.0
                },
                6
              ],
              "indent": 2,
              "code": 223
            },
            {
              "json_class": "RPG::EventCommand",
              "parameters": [],
              "indent": 2,
              "code": 115
            },
            {
              "json_class": "RPG::EventCommand",
              "parameters": [],
              "indent": 2,
              "code": 0
            },
            {
              "json_class": "RPG::EventCommand",
              "parameters": [],
              "indent": 1,
              "code": 411
            },
            {
              "json_class": "RPG::EventCommand",
              "parameters": [
                {
                  "json_class": "RPG::AudioFile",
                  "volume": 80,
                  "name": "Door exit",
                  "pitch": 100
                }
              ],
              "indent": 2,
              "code": 250
            },
            {
              "json_class": "RPG::EventCommand",
              "parameters": [
                {
                  "json_class": "Tone",
                  "red": -255.0,
                  "green": -255.0,
                  "blue": -255.0,
                  "gray": 0.0
                },
                6
              ],
              "indent": 2,
              "code": 223
            },
            {
              "json_class": "RPG::EventCommand",
              "parameters": [
                8
              ],
              "indent": 2,
              "code": 106
            },
            {
              "json_class": "RPG::EventCommand",
              "parameters": [
                0,
                65,
                4,
                5,
                8,
                1
              ],
              "indent": 2,
              "code": 201
            },
            {
              "json_class": "RPG::EventCommand",
              "parameters": [
                {
                  "json_class": "Tone",
                  "red": 0.0,
                  "green": 0.0,
                  "blue": 0.0,
                  "gray": 0.0
                },
                6
              ],
              "indent": 2,
              "code": 223
            },
            {
              "json_class": "RPG::EventCommand",
              "parameters": [],
              "indent": 2,
              "code": 115
            },
            {
              "json_class": "RPG::EventCommand",
              "parameters": [],
              "indent": 2,
              "code": 0
            },
            {
              "json_class": "RPG::EventCommand",
              "parameters": [],
              "indent": 1,
              "code": 412
            },
            {
              "json_class": "RPG::EventCommand",
              "parameters": [],
              "indent": 1,
              "code": 0
            },
            {
              "json_class": "RPG::EventCommand",
              "parameters": [],
              "indent": 0,
              "code": 411
            },
            {
              "json_class": "RPG::EventCommand",
              "parameters": [
                "pbBattleChallenge.setDecision(2)"
              ],
              "indent": 1,
              "code": 355
            },
            {
              "json_class": "RPG::EventCommand",
              "parameters": [
                {
                  "json_class": "RPG::AudioFile",
                  "volume": 80,
                  "name": "Door exit",
                  "pitch": 100
                }
              ],
              "indent": 1,
              "code": 250
            },
            {
              "json_class": "RPG::EventCommand",
              "parameters": [
                {
                  "json_class": "Tone",
                  "red": -255.0,
                  "green": -255.0,
                  "blue": -255.0,
                  "gray": 0.0
                },
                6
              ],
              "indent": 1,
              "code": 223
            },
            {
              "json_class": "RPG::EventCommand",
              "parameters": [
                8
              ],
              "indent": 1,
              "code": 106
            },
            {
              "json_class": "RPG::EventCommand",
              "parameters": [
                "pbBattleChallenge.pbGoToStart"
              ],
              "indent": 1,
              "code": 355
            },
            {
              "json_class": "RPG::EventCommand",
              "parameters": [
                {
                  "json_class": "Tone",
                  "red": 0.0,
                  "green": 0.0,
                  "blue": 0.0,
                  "gray": 0.0
                },
                6
              ],
              "indent": 1,
              "code": 223
            },
            {
              "json_class": "RPG::EventCommand",
              "parameters": [],
              "indent": 1,
              "code": 115
            },
            {
              "json_class": "RPG::EventCommand",
              "parameters": [],
              "indent": 1,
              "code": 0
            },
            {
              "json_class": "RPG::EventCommand",
              "parameters": [],
              "indent": 0,
              "code": 412
            },
            {
              "json_class": "RPG::EventCommand",
              "parameters": [],
              "indent": 0,
              "code": 0
            }
          ],
          "move_type": 0,
          "direction_fix": false,
          "condition": {
            "json_class": "RPG::Event::Page::Condition",
            "switch2_valid": false,
            "self_switch_ch": "A",
            "switch1_id": 1,
            "switch1_valid": false,
            "variable_value": 0,
            "self_switch_valid": false,
            "variable_id": 1,
            "variable_valid": false,
            "switch2_id": 1
          },
          "move_route": {
            "json_class": "RPG::MoveRoute",
            "list": [
              {
                "json_class": "RPG::MoveCommand",
                "parameters": [],
                "code": 0
              }
            ],
            "skippable": false,
            "repeat": true
          },
          "trigger": 3,
          "step_anime": false,
          "move_frequency": 3,
          "always_on_top": false,
          "graphic": {
            "json_class": "RPG::Event::Page::Graphic",
            "opacity": 255,
            "character_name": "trainer_SCIENTIST",
            "pattern": 0,
            "tile_id": 0,
            "direction": 8,
            "blend_type": 0,
            "character_hue": 0
          },
          "walk_anime": true,
          "move_speed": 3,
          "through": false
        }
      ],
      "name": "Guide",
      "y": 8,
      "x": 2,
      "id": 1
    },
    "2": {
      "json_class": "RPG::Event",
      "pages": [
        {
          "json_class": "RPG::Event::Page",
          "list": [
            {
              "json_class": "RPG::EventCommand",
              "parameters": [],
              "indent": 0,
              "code": 0
            }
          ],
          "move_type": 0,
          "direction_fix": false,
          "condition": {
            "json_class": "RPG::Event::Page::Condition",
            "switch2_valid": false,
            "self_switch_ch": "A",
            "switch1_id": 1,
            "switch1_valid": false,
            "variable_value": 0,
            "self_switch_valid": false,
            "variable_id": 1,
            "variable_valid": false,
            "switch2_id": 1
          },
          "move_route": {
            "json_class": "RPG::MoveRoute",
            "list": [
              {
                "json_class": "RPG::MoveCommand",
                "parameters": [],
                "code": 0
              }
            ],
            "skippable": false,
            "repeat": true
          },
          "trigger": 0,
          "step_anime": false,
          "move_frequency": 3,
          "always_on_top": false,
          "graphic": {
            "json_class": "RPG::Event::Page::Graphic",
            "opacity": 255,
            "character_name": "",
            "pattern": 0,
            "tile_id": 0,
            "direction": 2,
            "blend_type": 0,
            "character_hue": 0
          },
          "walk_anime": true,
          "move_speed": 3,
          "through": false
        }
      ],
      "name": "Opponent",
      "y": 1,
      "x": 12,
      "id": 2
    }
  },
  "tileset_id": 3,
  "bgs": {
    "json_class": "RPG::AudioFile",
    "volume": 80,
    "name": "",
    "pitch": 100
  },
  "autoplay_bgm": true,
  "data": {
    "json_class": "Table",
    "dim": 3,
    "x": 20,
    "y": 15,
    "z": 3,
    "data": [
      520,
      521,
      521,
      521,
      521,
      521,
      521,
      521,
      521,
      521,
      521,
      521,
      521,
      521,
      523,
      542,
      542,
      542,
      542,
      542,
      528,
      529,
      529,
      529,
      529,
      529,
      529,
      529,
      529,
      529,
      529,
      529,
      529,
      529,
      531,
      542,
      542,
      542,
      542,
      542,
      633,
      641,
      641,
      641,
      641,
      641,
      641,
      641,
      641,
      641,
      641,
      641,
      641,
      641,
      650,
      542,
      542,
      542,
      542,
      542,
      634,
      624,
      624,
      624,
      1081,
      1106,
      1106,
      1106,
      1106,
      1106,
      1083,
      635,
      624,
      624,
      624,
      542,
      542,
      542,
      542,
      542,
      634,
      624,
      624,
      624,
      1096,
      651,
      641,
      641,
      641,
      641,
      1096,
      634,
      624,
      624,
      624,
      542,
      542,
      542,
      542,
      542,
      634,
      624,
      624,
      624,
      649,
      642,
      624,
      624,
      624,
      624,
      649,
      642,
      624,
      624,
      624,
      542,
      542,
      542,
      542,
      542,
      634,
      624,
      624,
      624,
      1080,
      635,
      624,
      624,
      624,
      624,
      1080,
      635,
      624,
      624,
      624,
      542,
      542,
      542,
      542,
      542,
      634,
      624,
      624,
      624,
      1097,
      1106,
      1106,
      1106,
      1106,
      1106,
      1099,
      634,
      624,
      624,
      624,
      542,
      542,
      542,
      542,
      542,
      634,
      624,
      624,
      624,
      649,
      641,
      641,
      641,
      641,
      641,
      641,
      642,
      624,
      633,
      633,
      542,
      542,
      542,
      542,
      542,
      542,
      542,
      542,
      542,
      542,
      542,
      542,
      542,
      542,
      542,
      542,
      542,
      542,
      542,
      542,
      542,
      542,
      542,
      542,
      542,
      542,
      542,
      542,
      542,
      542,
      542,
      542,
      542,
      542,
      542,
      542,
      542,
      542,
      542,
      542,
      542,
      542,
      542,
      542,
      542,
      542,
      542,
      542,
      542,
      542,
      542,
      542,
      542,
      542,
      542,
      542,
      542,
      542,
      542,
      542,
      542,
      542,
      542,
      542,
      542,
      542,
      542,
      542,
      542,
      542,
      542,
      542,
      542,
      542,
      542,
      542,
      542,
      542,
      542,
      542,
      542,
      542,
      542,
      542,
      542,
      542,
      542,
      542,
      542,
      542,
      542,
      542,
      542,
      542,
      542,
      542,
      542,
      542,
      542,
      542,
      542,
      542,
      542,
      542,
      542,
      542,
      542,
      542,
      542,
      542,
      542,
      542,
      542,
      542,
      542,
      542,
      542,
      542,
      542,
      542,
      542,
      542,
      542,
      542,
      542,
      0,
      0,
      0,
      1788,
      0,
      0,
      0,
      0,
      0,
      0,
      1788,
      389,
      390,
      391,
      0,
      0,
      0,
      0,
      0,
      0,
      0,
      1794,
      1795,
      1796,
      0,
      1795,
      0,
      1794,
      1795,
      0,
      1796,
      397,
      398,
      399,
      1794,
      0,
      0,
      0,
      0,
      0,
      536,
      1802,
      1803,
      1804,
      0,
      1803,
      0,
      1802,
      1803,
      0,
      1804,
      0,
      0,
      0,
      1802,
      0,
      0,
      0,
      0,
      0,
      0,
      0,
      0,
      0,
      0,
      0,
      0,
      0,
      0,
      0,
      0,
      0,
      0,
      0,
      0,
      0,
      0,
      0,
      0,
      0,
      0,
      0,
      0,
      0,
      0,
      0,
      0,
      0,
      0,
      0,
      0,
      0,
      0,
      0,
      0,
      0,
      0,
      0,
      0,
      0,
      0,
      0,
      0,
      0,
      0,
      0,
      0,
      0,
      0,
      0,
      0,
      0,
      0,
      0,
      0,
      0,
      0,
      0,
      0,
      0,
      0,
      0,
      0,
      0,
      0,
      0,
      0,
      0,
      0,
      0,
      0,
      0,
      0,
      1784,
      1785,
      0,
      0,
      0,
      0,
      0,
      0,
      0,
      0,
      0,
      0,
      0,
      0,
      0,
      0,
      0,
      0,
      0,
      0,
      1792,
      1793,
      0,
      0,
      0,
      0,
      0,
      0,
      1245,
      1246,
      1247,
      0,
      0,
      0,
      0,
      0,
      0,
      0,
      0,
      0,
      1800,
      1801,
      0,
      0,
      0,
      0,
      0,
      0,
      1253,
      1254,
      1255,
      0,
      0,
      0,
      0,
      0,
      0,
      0,
      0,
      0,
      0,
      0,
      0,
      0,
      0,
      0,
      0,
      0,
      0,
      0,
      0,
      0,
      0,
      0,
      0,
      0,
      0,
      0,
      0,
      0,
      0,
      0,
      0,
      0,
      0,
      0,
      0,
      0,
      0,
      0,
      0,
      0,
      0,
      0,
      0,
      0,
      0,
      0,
      0,
      0,
      0,
      0,
      0,
      0,
      0,
      0,
      0,
      0,
      0,
      0,
      0,
      0,
      0,
      0,
      0,
      0,
      0,
      0,
      0,
      0,
      0,
      0,
      0,
      0,
      0,
      0,
      0,
      0,
      0,
      0,
      0,
      0,
      0,
      0,
      0,
      0,
      0,
      0,
      0,
      0,
      0,
      0,
      0,
      0,
      0,
      0,
      0,
      0,
      0,
      0,
      0,
      0,
      0,
      0,
      0,
      0,
      0,
      0,
      0,
      0,
      0,
      0,
      0,
      0,
      0,
      0,
      0,
      0,
      0,
      0,
      0,
      0,
      0,
      0,
      0,
      0,
      0,
      0,
      0,
      0,
      0,
      0,
      0,
      0,
      0,
      0,
      0,
      0,
      0,
      0,
      0,
      0,
      0,
      0,
      0,
      0,
      0,
      0,
      0,
      0,
      0,
      0,
      0,
      0,
      0,
      0,
      0,
      0,
      0,
      0,
      0,
      0,
      0,
      0,
      0,
      0,
      0,
      0,
      0,
      0,
      0,
      0,
      0,
      0,
      0,
      0,
      0,
      0,
      0,
      0,
      0,
      0,
      0,
      0,
      0,
      0,
      0,
      0,
      0,
      0,
      0,
      0,
      0,
      0,
      0,
      0,
      0,
      0,
      0,
      0,
      0,
      0,
      0,
      0,
      0,
      0,
      0,
      0,
      0,
      0,
      0,
      0,
      0,
      0,
      0,
      0,
      0,
      0,
      0,
      0,
      0,
      0,
      0,
      0,
      0,
      0,
      0,
      0,
      0,
      0,
      0,
      0,
      0,
      0,
      0,
      0,
      0,
      0,
      0,
      0,
      0,
      0,
      0,
      0,
      0,
      0,
      0,
      0,
      0,
      0,
      0,
      0,
      0,
      0,
      0,
      0,
      0,
      0,
      0,
      0,
      0,
      0,
      0,
      0,
      0,
      0,
      0,
      0,
      0,
      0,
      0,
      0,
      0,
      0,
      0,
      0,
      0,
      0,
      0,
      0,
      0,
      0,
      0,
      0,
      0,
      0,
      0,
      0,
      0,
      0,
      0,
      0,
      0,
      0,
      0,
      0,
      0,
      0,
      0,
      0,
      0,
      0,
      0,
      0,
      0,
      0,
      0,
      0,
      0,
      0,
      0,
      0,
      0,
      0,
      0,
      0,
      0,
      0,
      0,
      0,
      0,
      0,
      0,
      0,
      0,
      0,
      0,
      0,
      0,
      0,
      0,
      0,
      0,
      0,
      0,
      0,
      0,
      0,
      0,
      0,
      0,
      0,
      0,
      0,
      0,
      0,
      0,
      0,
      0,
      0,
      0,
      0,
      0,
      0,
      0,
      0,
      0,
      0,
      0,
      0,
      0,
      0,
      0,
      0,
      0,
      0,
      0,
      0,
      0,
      0,
      0,
      0,
      0,
      0,
      0,
      0,
      0,
      0,
      0,
      0,
      0,
      0,
      0,
      0,
      0,
      0,
      0,
      0,
      0,
      0,
      0,
      0,
      0,
      0,
      0,
      0,
      0,
      0,
      0,
      0,
      0,
      0,
      0,
      0,
      0,
      0,
      0,
      0,
      0,
      0,
      0,
      0,
      0,
      0,
      0,
      0,
      0
    ]
  },
  "autoplay_bgs": false,
  "height": 15,
  "encounter_step": 30,
  "width": 20,
  "encounter_list": []
}